{"tables":[{"id":1,"number":"T1","type":"standard","capacity":4,"coord_x":10,"coord_y":10,"status":"available","zone":"Main Hall"},{"id":2,"number":"T2","type":"standard","capacity":4,"coord_x":30,"coord_y":10,"status":"available","zone":"Main Hall"},{"id":3,"number":"T3","type":"standard","capacity":4,"coord_x":50,"coord_y":10,"status":"available","zone":"Main Hall"},{"id":4,"number":"T4","type":"standard","capacity":2,"coord_x":10,"coord_y":40,"status":"available","zone":"Window View"},{"id":5,"number":"T5","type":"standard","capacity":2,"coord_x":30,"coord_y":40,"status":"available","zone":"Window View"},{"id":6,"number":"VIP1","type":"vip","capacity":4,"coord_x":70,"coord_y":10,"status":"available","zone":"VIP Lounge"},{"id":7,"number":"VIP2","type":"vip","capacity":4,"coord_x":90,"coord_y":10,"status":"available","zone":"VIP Lounge"},{"id":8,"number":"LG1","type":"large_group","capacity":12,"coord_x":60,"coord_y":60,"status":"incompatible","zone":"Party Zone"},{"id":9,"number":"LG2","type":"large_group","capacity":15,"coord_x":80,"coord_y":60,"status":"incompatible","zone":"Party Zone"},{"id":10,"number":"M1","type":"standard","capacity":8,"coord_x":20,"coord_y":70,"status":"available","zone":"Main Hall"},{"id":11,"number":"M2","type":"standard","capacity":6,"coord_x":40,"coord_y":70,"status":"available","zone":"Main Hall"}]}